{
  "field_name": "maxRetxThreshold",
  "field_path": "message[1][1].criticalExtensions[1].masterCellGroup[1].rlc-BearerToAddModList[0].rlc-Config[1].ul-AM-RLC.maxRetxThreshold",
  "asn1_rules": {
    "rules": [
      {
        "field_name": "maxRetxThreshold",
        "type": "ENUM",
        "range": [
          null
        ],
        "available_options": [
          "t1",
          "t2",
          "t3",
          "t4",
          "t6",
          "t8",
          "t16",
          "t32"
        ],
        "additional_constraints": "XXX"
      }
    ]
  },
  "importance_score": 0,
  "category": "XXX",
  "reason": "The 'maxRetxThreshold' field is XXX"
}