{
  "field_name": "firstOFDMSymbolInTimeDomain",
  "field_path": "message[1][1].criticalExtensions[1].masterCellGroup[1].spCellConfig.spCellConfigDedicated.csi-MeasConfig[1].nzp-CSI-RS-ResourceToAddModList[2].resourceMapping.firstOFDMSymbolInTimeDomain",
  "asn1_rules": {
    "rules": [
      {
        "field_name": "firstOFDMSymbolInTimeDomain",
        "type": "INT",
        "range": [
          0,
          13
        ],
        "available_options": [
          null
        ],
        "additional_constraints": "XXX"
      }
    ]
  },
  "importance_score": 0,
  "category": "XXX",
  "reason": "The 'firstOFDMSymbolInTimeDomain' field is XXX"
}